django_api_helper/__init__.py
django_api_helper/admin.py
django_api_helper/apps.py
django_api_helper/decorators.py
django_api_helper/filters.py
django_api_helper/models.py
django_api_helper/pagination.py
django_api_helper/resources.py
django_api_helper/serializers.py
django_api_helper/tests.py
django_api_helper/urls.py
django_api_helper/views.py
django_api_helper/migrations/__init__.py
django_api_helper-0.1.0.dist-info/METADATA
django_api_helper-0.1.0.dist-info/WHEEL
django_api_helper-0.1.0.dist-info/top_level.txt
django_api_helper-0.1.0.dist-info/RECORD
