Metadata-Version: 2.4
Name: django-api-helper
Version: 0.1.0
Summary: An abstraction layer for creating APIs in Django Rest Framework, supports rpc style APIs.
Home-page: https://github.com/RuchitMicro/django-api-helper
Author: Ruchit Kharwa
Author-email: ruchit@wolfx.io
Classifier: Programming Language :: Python :: 3
Classifier: Framework :: Django
Classifier: License :: OSI Approved :: MIT License
Classifier: Operating System :: OS Independent
Requires-Python: >=3.6
Requires-Dist: django>=3.0
Requires-Dist: django-api-helper
Requires-Dist: django-filter
Dynamic: author
Dynamic: author-email
Dynamic: classifier
Dynamic: description
Dynamic: description-content-type
Dynamic: home-page
Dynamic: requires-dist
Dynamic: requires-python
Dynamic: summary
